letsbuilda/pypi/__init__.py
letsbuilda/pypi/async_client.py
letsbuilda/pypi/exceptions.py
letsbuilda/pypi/py.typed
letsbuilda/pypi/sync_client.py
letsbuilda/pypi/models/__init__.py
letsbuilda/pypi/models/models_json.py
letsbuilda/pypi/models/models_package.py
letsbuilda/pypi/models/models_rss.py
letsbuilda_pypi-5.2.1.dist-info/LICENSE
letsbuilda_pypi-5.2.1.dist-info/METADATA
letsbuilda_pypi-5.2.1.dist-info/WHEEL
letsbuilda_pypi-5.2.1.dist-info/top_level.txt
letsbuilda_pypi-5.2.1.dist-info/RECORD
