Metadata-Version: 2.1
Name: letsbuilda-pypi
Version: 5.2.1
Summary: A wrapper for PyPI's API and RSS feed
Author-email: Bradley Reynolds <bradley.reynolds@darbia.dev>
License: MIT
Project-URL: repository, https://github.com/letsbuilda/letsbuilda-pypi/
Project-URL: documentation, https://docs.letsbuilda.dev/letsbuilda-pypi/
Requires-Python: >=3.11
License-File: LICENSE
Requires-Dist: httpx
Requires-Dist: xmltodict
Provides-Extra: dev
Requires-Dist: pre-commit; extra == "dev"
Requires-Dist: ruff; extra == "dev"
Requires-Dist: mypy; extra == "dev"
Requires-Dist: types-xmltodict; extra == "dev"
Provides-Extra: docs
Requires-Dist: sphinx; extra == "docs"
Requires-Dist: furo; extra == "docs"
Requires-Dist: sphinx-autoapi; extra == "docs"
Requires-Dist: releases; extra == "docs"
Provides-Extra: tests
Requires-Dist: pytest; extra == "tests"
